grasp_planning/__init__.py
grasp_planning/constraints/angle_between_vectors_constraint.py
grasp_planning/constraints/collision_constraint.py
grasp_planning/constraints/constraint_template.py
grasp_planning/constraints/constraints.py
grasp_planning/constraints/grasp_pos_constraint.py
grasp_planning/constraints/grasp_rot_constraint.py
grasp_planning/constraints/manipulation_constraint.py
grasp_planning/constraints/orientation_constraint.py
grasp_planning/constraints/position_constraint.py
grasp_planning/constraints/postgrasp_constraint.py
grasp_planning/constraints/pregrasp_constraint.py
grasp_planning/constraints/z_height_constraint.py
grasp_planning/cost/costs.py
grasp_planning/cost/dist_to_home.py
grasp_planning/cost/squared_acc_cost.py
grasp_planning/solver/gomp_planner.py
grasp_planning/solver/ik_optim.py
grasp_planning/solver/robot_model.py
grasp_planning-0.7.0.dist-info/METADATA
grasp_planning-0.7.0.dist-info/WHEEL
grasp_planning-0.7.0.dist-info/RECORD
